{
  "plan_id": "H4514-014",
  "carrier": "UnitedHealthcare",
  "contract_number": "H4514",
  "org_name": "UNITEDHEALTHCARE COMMUNITY PLAN OF TEXAS, L.L.C.",
  "geographic_area": "Select Counties in Texas",
  "states": "TX",
  "counties_count": "4",
  "source": "CMS PBP 2026",
  "star_rating_overall": 4.0,
  "star_rating_part_c": 4.0,
  "star_rating_part_d": 3.5,
  "plan_name": "AARP® Medicare Advantage from UHC TX-001P (HMO-POS)",
  "plan_type": "HMO-POS",
  "monthly_premium": "$0",
  "annual_deductible_in": "$0 medical, $0 Tier 1-2 drugs, $440 Tier 3-5 drugs",
  "moop_in": "$4,500",
  "moop_out": "Not specified",
  "drug_deductible": "$440",
  "sections": [
    {
      "title": "Key Benefits",
      "icon": "heart-pulse",
      "rows": [
        {
          "label": "PCP visit",
          "value": "$0"
        },
        {
          "label": "Specialist visit",
          "value": "$30"
        },
        {
          "label": "Emergency room (in-network)",
          "value": "$130"
        },
        {
          "label": "Emergency room (out-of-network)",
          "value": "$0 outside US"
        },
        {
          "label": "Urgent care (in-network)",
          "value": "$50"
        },
        {
          "label": "Urgent care (out-of-network)",
          "value": "$0 outside US"
        },
        {
          "label": "Inpatient hospital",
          "value": "$450 per stay"
        },
        {
          "label": "Mental health inpatient",
          "value": "$450 per stay"
        },
        {
          "label": "Ambulance ground",
          "value": "$275"
        },
        {
          "label": "Ambulance air",
          "value": "$275"
        }
      ]
    },
    {
      "title": "Dental",
      "icon": "tooth",
      "rows": [
        {
          "label": "Dental allowance",
          "value": "$3,000 allowance for all covered dental services"
        }
      ]
    },
    {
      "title": "Vision",
      "icon": "eye",
      "rows": [
        {
          "label": "Vision eyewear allowance",
          "value": "$200 allowance every 2 years for frames or contacts"
        }
      ]
    },
    {
      "title": "Supplemental Benefits",
      "icon": "hand-holding-heart",
      "rows": [
        {
          "label": "OTC allowance",
          "value": "$40 credit every quarter"
        },
        {
          "label": "Fitness program",
          "value": "$0 copay - free gym membership"
        },
        {
          "label": "Meal benefit",
          "value": "Covered — see Summary of Benefits"
        },
        {
          "label": "UnitedHealth Passport",
          "value": "Travel coverage up to 9 consecutive months in service area"
        },
        {
          "label": "Member discounts",
          "value": "Discounts on hundreds of products and services"
        }
      ]
    },
    {
      "title": "Diagnostic Tests & Imaging",
      "icon": "microscope",
      "rows": [
        {
          "label": "Lab services",
          "value": "$0"
        },
        {
          "label": "X-rays",
          "value": "$30"
        },
        {
          "label": "Diagnostic tests",
          "value": "$50"
        },
        {
          "label": "Advanced imaging",
          "value": "$0 diagnostic mammogram, $240 otherwise"
        },
        {
          "label": "Therapeutic radiology",
          "value": "20%"
        }
      ]
    },
    {
      "title": "Specialty & Therapy Care",
      "icon": "stethoscope",
      "rows": [
        {
          "label": "Mental health outpatient individual",
          "value": "$25"
        },
        {
          "label": "Mental health outpatient group",
          "value": "$15"
        },
        {
          "label": "Virtual mental health",
          "value": "$0"
        },
        {
          "label": "Substance abuse outpatient individual",
          "value": "$25"
        },
        {
          "label": "Substance abuse outpatient group",
          "value": "$15"
        },
        {
          "label": "Physical therapy",
          "value": "$20"
        },
        {
          "label": "Occupational therapy",
          "value": "$20"
        },
        {
          "label": "Speech therapy",
          "value": "$20"
        },
        {
          "label": "Chiropractic",
          "value": "$15"
        },
        {
          "label": "Podiatry",
          "value": "$30"
        },
        {
          "label": "Opioid treatment program",
          "value": "$0"
        }
      ]
    },
    {
      "title": "Home & Post-Acute Care",
      "icon": "house-medical",
      "rows": [
        {
          "label": "Skilled nursing facility",
          "value": "$0 days 1-20, $218 days 21-100"
        },
        {
          "label": "Home health care",
          "value": "$0"
        },
        {
          "label": "Hospice",
          "value": "$0"
        },
        {
          "label": "DME",
          "value": "20%"
        },
        {
          "label": "Kidney disease/dialysis",
          "value": "20%"
        }
      ]
    },
    {
      "title": "Other Medical Services",
      "icon": "hospital",
      "rows": [
        {
          "label": "Preventive care",
          "value": "$0"
        },
        {
          "label": "Virtual medical visits",
          "value": "$0"
        },
        {
          "label": "Outpatient surgery ASC",
          "value": "$0 colonoscopy, $400 otherwise"
        },
        {
          "label": "Outpatient hospital surgery",
          "value": "$0 colonoscopy, $450 otherwise"
        },
        {
          "label": "Outpatient observation",
          "value": "$450"
        },
        {
          "label": "Routine foot care",
          "value": "$30, 6 visits/year"
        },
        {
          "label": "Diabetic supplies",
          "value": "$0"
        },
        {
          "label": "Diabetic self-management training",
          "value": "$0"
        },
        {
          "label": "Diabetic therapeutic shoes",
          "value": "20%"
        },
        {
          "label": "Prosthetics",
          "value": "20%"
        }
      ]
    },
    {
      "title": "Prescription Drugs",
      "icon": "pills",
      "rows": [
        {
          "label": "Tier 1 Preferred Generic 30-day retail",
          "value": "$0"
        },
        {
          "label": "Tier 1 Preferred Generic 100-day retail",
          "value": "$0"
        },
        {
          "label": "Tier 1 Preferred Generic 100-day mail",
          "value": "$0"
        },
        {
          "label": "Tier 2 Generic 30-day retail",
          "value": "$0"
        },
        {
          "label": "Tier 2 Generic 100-day retail",
          "value": "$0"
        },
        {
          "label": "Tier 2 Generic 100-day mail",
          "value": "$0"
        },
        {
          "label": "Tier 3 Preferred Brand 30-day retail",
          "value": "18%"
        },
        {
          "label": "Tier 3 Preferred Brand 100-day retail",
          "value": "18%"
        },
        {
          "label": "Tier 3 Preferred Brand 100-day mail",
          "value": "18%"
        },
        {
          "label": "Tier 4 Non-Preferred Drug 30-day retail",
          "value": "41%"
        },
        {
          "label": "Tier 5 Specialty 30-day retail",
          "value": "28%"
        },
        {
          "label": "Covered Insulin 30-day retail",
          "value": "18%, up to $35"
        },
        {
          "label": "Covered Insulin 100-day retail",
          "value": "18%, up to $105"
        },
        {
          "label": "Covered Insulin 100-day mail",
          "value": "18%, up to $105"
        },
        {
          "label": "Catastrophic Coverage",
          "value": "$0"
        },
        {
          "label": "Part B chemotherapy drugs",
          "value": "20%"
        },
        {
          "label": "Part B insulin",
          "value": "20%, up to $35"
        },
        {
          "label": "Part B allergy antigens",
          "value": "$0"
        },
        {
          "label": "Other Part B drugs",
          "value": "20%"
        }
      ]
    },
    {
      "title": "Plan Resources",
      "icon": "phone",
      "rows": [
        {
          "label": "Member Phone",
          "value": "(866)550-4736"
        },
        {
          "label": "Member Phone (Local)",
          "value": "(866)550-4736"
        },
        {
          "label": "Prospective Member Phone",
          "value": "(800)555-5757"
        },
        {
          "label": "TTY",
          "value": "711"
        },
        {
          "label": "Provider Directory",
          "value": "AARPMedicarePlans.com"
        },
        {
          "label": "Formulary",
          "value": "AARPMedicarePlans.com"
        },
        {
          "label": "Pharmacy Directory",
          "value": "AARPMedicarePlans.com"
        },
        {
          "label": "Website",
          "value": "AARPMedicarePlans.com"
        }
      ]
    }
  ]
}