{
  "plan_id": "H1608-029",
  "carrier": "Aetna Medicare",
  "contract_number": "H1608",
  "org_name": "COVENTRY HEALTH AND LIFE INSURANCE COMPANY",
  "geographic_area": "Northeastern and Youngstown Area",
  "states": "OH",
  "counties_count": "11",
  "source": "CMS PBP 2026",
  "star_rating_overall": 3.5,
  "star_rating_part_c": 3.5,
  "star_rating_part_d": 3.5,
  "plan_name": "Aetna Medicare Advantra (PPO)",
  "plan_type": "PPO",
  "monthly_premium": "$0",
  "annual_deductible_in": "$0",
  "moop_in": "$4,500",
  "moop_out": "$8,950",
  "moop_combined": "$8,950",
  "drug_deductible": "$615",
  "sections": [
    {
      "title": "Key Benefits",
      "icon": "heart-pulse",
      "rows": [
        {
          "label": "PCP visit (in-network)",
          "value": "$0"
        },
        {
          "label": "PCP visit (out-of-network)",
          "value": "50%"
        },
        {
          "label": "Specialist visit (in-network)",
          "value": "$40"
        },
        {
          "label": "Specialist visit (out-of-network)",
          "value": "50%"
        },
        {
          "label": "Urgent care (in-network)",
          "value": "$50"
        },
        {
          "label": "Urgent care (out-of-network)",
          "value": "$130"
        },
        {
          "label": "Emergency room",
          "value": "$130"
        },
        {
          "label": "Inpatient hospital (in-network)",
          "value": "$275/day days 1-7, $0/day days 8-90"
        },
        {
          "label": "Inpatient hospital (out-of-network)",
          "value": "50%"
        },
        {
          "label": "Ambulance ground",
          "value": "$235"
        },
        {
          "label": "Ambulance air",
          "value": "20%"
        },
        {
          "label": "Mental health inpatient (in-network)",
          "value": "$275/day days 1-7, $0/day days 8-90"
        },
        {
          "label": "Mental health inpatient (out-of-network)",
          "value": "50%"
        }
      ]
    },
    {
      "title": "Dental",
      "icon": "tooth",
      "rows": [
        {
          "label": "Dental comprehensive allowance",
          "value": "$2,000 per year"
        }
      ]
    },
    {
      "title": "Vision",
      "icon": "eye",
      "rows": [
        {
          "label": "Vision eyewear allowance",
          "value": "$175 per year"
        }
      ]
    },
    {
      "title": "Hearing",
      "icon": "ear-listen",
      "rows": [
        {
          "label": "Hearing aids allowance",
          "value": "$1,250 per ear per year"
        }
      ]
    },
    {
      "title": "Supplemental Benefits",
      "icon": "hand-holding-heart",
      "rows": [
        {
          "label": "OTC allowance",
          "value": "$50 per quarter"
        },
        {
          "label": "Podiatry non-Medicare visits",
          "value": "Up to 6 visits per year"
        },
        {
          "label": "SilverSneakers fitness membership",
          "value": "$0 copay basic membership"
        },
        {
          "label": "24-Hour Nurse Line",
          "value": "$0 copay"
        },
        {
          "label": "Resources For Living",
          "value": "Community resource connection service"
        },
        {
          "label": "Worldwide emergency coverage",
          "value": "Maximum $250,000 coverage"
        },
        {
          "label": "Visitor/travel program Explorer",
          "value": "Up to 12 months outside service area"
        }
      ]
    },
    {
      "title": "Diagnostic Tests & Imaging",
      "icon": "microscope",
      "rows": [
        {
          "label": "Lab services (in-network)",
          "value": "$0"
        },
        {
          "label": "Lab services (out-of-network)",
          "value": "50%"
        },
        {
          "label": "X-rays non-hospital (in-network)",
          "value": "$5"
        },
        {
          "label": "X-rays non-hospital (out-of-network)",
          "value": "50%"
        },
        {
          "label": "X-rays hospital (in-network)",
          "value": "$90"
        },
        {
          "label": "X-rays hospital (out-of-network)",
          "value": "50%"
        },
        {
          "label": "Advanced imaging CT/MRI (in-network)",
          "value": "$100"
        },
        {
          "label": "Advanced imaging CT/MRI (out-of-network)",
          "value": "50%"
        },
        {
          "label": "Diagnostic tests (in-network)",
          "value": "$175"
        },
        {
          "label": "Diagnostic tests (out-of-network)",
          "value": "50%"
        },
        {
          "label": "Glaucoma screening (in-network)",
          "value": "$0"
        },
        {
          "label": "Glaucoma screening (out-of-network)",
          "value": "50%"
        }
      ]
    },
    {
      "title": "Specialty & Therapy Care",
      "icon": "stethoscope",
      "rows": [
        {
          "label": "Mental health outpatient individual (in-network)",
          "value": "$40"
        },
        {
          "label": "Mental health outpatient individual (out-of-network)",
          "value": "50%"
        },
        {
          "label": "Mental health outpatient group (in-network)",
          "value": "$40"
        },
        {
          "label": "Mental health outpatient group (out-of-network)",
          "value": "50%"
        },
        {
          "label": "Substance abuse outpatient individual (in-network)",
          "value": "$40"
        },
        {
          "label": "Substance abuse outpatient individual (out-of-network)",
          "value": "50%"
        },
        {
          "label": "Substance abuse outpatient group (in-network)",
          "value": "$40"
        },
        {
          "label": "Substance abuse outpatient group (out-of-network)",
          "value": "50%"
        },
        {
          "label": "Physical therapy (in-network)",
          "value": "$40"
        },
        {
          "label": "Physical therapy (out-of-network)",
          "value": "50%"
        },
        {
          "label": "Occupational therapy (in-network)",
          "value": "$40"
        },
        {
          "label": "Occupational therapy (out-of-network)",
          "value": "50%"
        },
        {
          "label": "Speech therapy (in-network)",
          "value": "$40"
        },
        {
          "label": "Speech therapy (out-of-network)",
          "value": "50%"
        },
        {
          "label": "Chiropractic (in-network)",
          "value": "$15"
        },
        {
          "label": "Chiropractic (out-of-network)",
          "value": "50%"
        },
        {
          "label": "Podiatry Medicare-covered (in-network)",
          "value": "$40"
        },
        {
          "label": "Podiatry Medicare-covered (out-of-network)",
          "value": "50%"
        },
        {
          "label": "Podiatry non-Medicare (in-network)",
          "value": "$40"
        },
        {
          "label": "Podiatry non-Medicare (out-of-network)",
          "value": "50%"
        },
        {
          "label": "Acupuncture (in-network)",
          "value": "$40"
        },
        {
          "label": "Acupuncture (out-of-network)",
          "value": "50%"
        }
      ]
    },
    {
      "title": "Home & Post-Acute Care",
      "icon": "house-medical",
      "rows": [
        {
          "label": "Skilled nursing facility (in-network)",
          "value": "$0/day days 1-20, $218/day days 21-100"
        },
        {
          "label": "Skilled nursing facility (out-of-network)",
          "value": "50%"
        },
        {
          "label": "Home health care (in-network)",
          "value": "$0"
        },
        {
          "label": "Home health care (out-of-network)",
          "value": "50%"
        },
        {
          "label": "Durable medical equipment (in-network)",
          "value": "0%-20%"
        },
        {
          "label": "Durable medical equipment (out-of-network)",
          "value": "50%"
        }
      ]
    },
    {
      "title": "Other Medical Services",
      "icon": "hospital",
      "rows": [
        {
          "label": "Preventive care (in-network)",
          "value": "$0"
        },
        {
          "label": "Preventive care (out-of-network)",
          "value": "0%-50%"
        },
        {
          "label": "Outpatient hospital services (in-network)",
          "value": "$35"
        },
        {
          "label": "Outpatient hospital services (out-of-network)",
          "value": "50%"
        },
        {
          "label": "Outpatient surgery (in-network)",
          "value": "$275"
        },
        {
          "label": "Outpatient surgery (out-of-network)",
          "value": "50%"
        },
        {
          "label": "Ambulatory surgical center (in-network)",
          "value": "$245"
        },
        {
          "label": "Ambulatory surgical center (out-of-network)",
          "value": "50%"
        },
        {
          "label": "Outpatient hospital observation (in-network)",
          "value": "$275"
        },
        {
          "label": "Outpatient hospital observation (out-of-network)",
          "value": "50%"
        },
        {
          "label": "Prosthetics (in-network)",
          "value": "20%"
        },
        {
          "label": "Prosthetics (out-of-network)",
          "value": "50%"
        },
        {
          "label": "Diabetic supplies preferred",
          "value": "0%"
        },
        {
          "label": "Diabetic supplies other",
          "value": "20%"
        }
      ]
    },
    {
      "title": "Prescription Drugs",
      "icon": "pills",
      "rows": [
        {
          "label": "Drug deductible",
          "value": "$615 Tiers 3-5 only"
        },
        {
          "label": "Tier 1 Preferred Generic 30-day preferred retail",
          "value": "$0"
        },
        {
          "label": "Tier 1 Preferred Generic 30-day standard retail",
          "value": "$2"
        },
        {
          "label": "Tier 1 Preferred Generic 100-day preferred retail",
          "value": "$0"
        },
        {
          "label": "Tier 1 Preferred Generic 100-day standard retail",
          "value": "$6"
        },
        {
          "label": "Tier 2 Generic 30-day preferred retail",
          "value": "$0"
        },
        {
          "label": "Tier 2 Generic 30-day standard retail",
          "value": "$12"
        },
        {
          "label": "Tier 2 Generic 100-day preferred retail",
          "value": "$0"
        },
        {
          "label": "Tier 2 Generic 100-day standard retail",
          "value": "$36"
        },
        {
          "label": "Tier 3 Preferred Brand all pharmacies",
          "value": "24%"
        },
        {
          "label": "Tier 4 Non-Preferred Drug all pharmacies",
          "value": "25%"
        },
        {
          "label": "Tier 5 Specialty all pharmacies",
          "value": "25%"
        },
        {
          "label": "Part B insulin",
          "value": "$35"
        },
        {
          "label": "Part B chemotherapy drugs",
          "value": "0%-20%"
        },
        {
          "label": "Part B other drugs",
          "value": "0%-20%"
        },
        {
          "label": "Catastrophic phase",
          "value": "$0"
        }
      ]
    },
    {
      "title": "Plan Resources",
      "icon": "phone",
      "rows": [
        {
          "label": "Member Phone",
          "value": "(833)570-6670"
        },
        {
          "label": "Member Phone (Local)",
          "value": "(833)570-6670"
        },
        {
          "label": "Prospective Member Phone",
          "value": "(833)859-6031"
        },
        {
          "label": "TTY",
          "value": "711"
        },
        {
          "label": "Provider Directory",
          "value": "www.aetnamedicare.com/findprovider"
        },
        {
          "label": "Formulary",
          "value": "www.aetnamedicare.com/formulary"
        },
        {
          "label": "Pharmacy Directory",
          "value": "www.aetnamedicare.com/findpharmacy"
        },
        {
          "label": "Website",
          "value": "www.aetna.com/medicare"
        }
      ]
    }
  ]
}