{
  "plan_id": "H5521-492",
  "carrier": "Aetna Medicare",
  "contract_number": "H5521",
  "org_name": "AETNA LIFE INSURANCE COMPANY",
  "geographic_area": "Greater Portland Metro Area",
  "states": "OR",
  "counties_count": "5",
  "source": "CMS PBP 2026",
  "star_rating_overall": 4.5,
  "star_rating_part_c": 4.5,
  "star_rating_part_d": 5.0,
  "plan_name": "Aetna Medicare Signature (PPO)",
  "plan_type": "PPO",
  "monthly_premium": "$0",
  "annual_deductible_in": "$0",
  "moop_in": "$6,900",
  "moop_out": "$13,900",
  "moop_combined": "$13,900",
  "drug_deductible": "$615",
  "sections": [
    {
      "title": "Key Benefits",
      "icon": "heart-pulse",
      "rows": [
        {
          "label": "PCP visit (in-network)",
          "value": "$0"
        },
        {
          "label": "PCP visit (out-of-network)",
          "value": "50%"
        },
        {
          "label": "Specialist visit (in-network)",
          "value": "$55"
        },
        {
          "label": "Specialist visit (out-of-network)",
          "value": "50%"
        },
        {
          "label": "Urgent care",
          "value": "$40"
        },
        {
          "label": "Emergency room",
          "value": "$115"
        },
        {
          "label": "Inpatient hospital (in-network)",
          "value": "$475/day days 1-5, $0/day days 6-90"
        },
        {
          "label": "Inpatient hospital (out-of-network)",
          "value": "50% per stay"
        },
        {
          "label": "Ambulance",
          "value": "$280 ground, 20% air"
        },
        {
          "label": "Mental health (inpatient) (in-network)",
          "value": "$415/day days 1-5, $0/day days 6-90"
        },
        {
          "label": "Mental health (inpatient) (out-of-network)",
          "value": "50% per stay"
        }
      ]
    },
    {
      "title": "Dental",
      "icon": "tooth",
      "rows": [
        {
          "label": "Dental allowance",
          "value": "$1,250 annual for comprehensive services"
        }
      ]
    },
    {
      "title": "Supplemental Benefits",
      "icon": "hand-holding-heart",
      "rows": [
        {
          "label": "OTC allowance",
          "value": "$25 quarterly"
        },
        {
          "label": "Fitness benefit",
          "value": "SilverSneakers membership at no cost"
        },
        {
          "label": "24-Hour Nurse Line",
          "value": "Available at no cost"
        },
        {
          "label": "Resources For Living",
          "value": "Community resource connection service"
        },
        {
          "label": "Visitor/travel program",
          "value": "Explorer - up to 12 months outside service area"
        },
        {
          "label": "Worldwide emergency coverage",
          "value": "$250,000 maximum coverage"
        }
      ]
    },
    {
      "title": "Diagnostic Tests & Imaging",
      "icon": "microscope",
      "rows": [
        {
          "label": "Lab services (in-network)",
          "value": "$25, $0 certain tests"
        },
        {
          "label": "Lab services (out-of-network)",
          "value": "50%"
        },
        {
          "label": "X-rays/diagnostic imaging (in-network)",
          "value": "$0"
        },
        {
          "label": "X-rays/diagnostic imaging (out-of-network)",
          "value": "50%"
        },
        {
          "label": "Advanced imaging (CT/MRI/PET) (in-network)",
          "value": "$325"
        },
        {
          "label": "Advanced imaging (CT/MRI/PET) (out-of-network)",
          "value": "50%"
        },
        {
          "label": "Diagnostic tests (in-network)",
          "value": "$25, $0 certain tests"
        },
        {
          "label": "Diagnostic tests (out-of-network)",
          "value": "50%"
        }
      ]
    },
    {
      "title": "Specialty & Therapy Care",
      "icon": "stethoscope",
      "rows": [
        {
          "label": "Mental health (outpatient) (in-network)",
          "value": "$40"
        },
        {
          "label": "Mental health (outpatient) (out-of-network)",
          "value": "50%"
        },
        {
          "label": "Substance abuse (outpatient) (in-network)",
          "value": "$40"
        },
        {
          "label": "Substance abuse (outpatient) (out-of-network)",
          "value": "50%"
        },
        {
          "label": "Chiropractic (in-network)",
          "value": "$10"
        },
        {
          "label": "Chiropractic (out-of-network)",
          "value": "50%"
        },
        {
          "label": "Podiatry/foot care (in-network)",
          "value": "$55"
        },
        {
          "label": "Podiatry/foot care (out-of-network)",
          "value": "50%"
        },
        {
          "label": "Physical therapy (in-network)",
          "value": "$35"
        },
        {
          "label": "Physical therapy (out-of-network)",
          "value": "50%"
        },
        {
          "label": "Occupational therapy (in-network)",
          "value": "$35"
        },
        {
          "label": "Occupational therapy (out-of-network)",
          "value": "50%"
        },
        {
          "label": "Speech therapy (in-network)",
          "value": "$35"
        },
        {
          "label": "Speech therapy (out-of-network)",
          "value": "50%"
        },
        {
          "label": "Acupuncture (in-network)",
          "value": "$55 Medicare-covered, non-Medicare not covered"
        },
        {
          "label": "Acupuncture (out-of-network)",
          "value": "50% Medicare-covered"
        }
      ]
    },
    {
      "title": "Home & Post-Acute Care",
      "icon": "house-medical",
      "rows": [
        {
          "label": "Skilled nursing facility (in-network)",
          "value": "$0/day days 1-20, $218/day days 21-100"
        },
        {
          "label": "Skilled nursing facility (out-of-network)",
          "value": "50% per stay"
        },
        {
          "label": "Home health care (in-network)",
          "value": "$0"
        },
        {
          "label": "Home health care (out-of-network)",
          "value": "50%"
        },
        {
          "label": "Durable medical equipment (DME) (in-network)",
          "value": "20%"
        },
        {
          "label": "Durable medical equipment (DME) (out-of-network)",
          "value": "50%"
        }
      ]
    },
    {
      "title": "Other Medical Services",
      "icon": "hospital",
      "rows": [
        {
          "label": "Preventive care (in-network)",
          "value": "$0"
        },
        {
          "label": "Preventive care (out-of-network)",
          "value": "0%-50%"
        },
        {
          "label": "Outpatient surgery/services (in-network)",
          "value": "$450"
        },
        {
          "label": "Outpatient surgery/services (out-of-network)",
          "value": "50%"
        },
        {
          "label": "Ambulatory surgical center (in-network)",
          "value": "$375"
        },
        {
          "label": "Ambulatory surgical center (out-of-network)",
          "value": "50%"
        },
        {
          "label": "Outpatient observation (in-network)",
          "value": "$475"
        },
        {
          "label": "Outpatient observation (out-of-network)",
          "value": "50%"
        },
        {
          "label": "Prosthetics/orthotics (in-network)",
          "value": "20%"
        },
        {
          "label": "Prosthetics/orthotics (out-of-network)",
          "value": "50%"
        },
        {
          "label": "Diabetic supplies/monitoring",
          "value": "0%-20%"
        }
      ]
    },
    {
      "title": "Prescription Drugs",
      "icon": "pills",
      "rows": [
        {
          "label": "Drug deductible",
          "value": "$615 (Tiers 3,4,5)"
        },
        {
          "label": "Tier 1 Preferred Generic - 30-day Preferred Retail",
          "value": "$0"
        },
        {
          "label": "Tier 1 Preferred Generic - 30-day Standard Retail",
          "value": "$2"
        },
        {
          "label": "Tier 1 Preferred Generic - 30-day Preferred Mail",
          "value": "$0"
        },
        {
          "label": "Tier 1 Preferred Generic - 30-day Standard Mail",
          "value": "$2"
        },
        {
          "label": "Tier 1 Preferred Generic - 31-day LTC",
          "value": "$2"
        },
        {
          "label": "Tier 1 Preferred Generic - 100-day Preferred Retail",
          "value": "$0"
        },
        {
          "label": "Tier 1 Preferred Generic - 100-day Standard Retail",
          "value": "$6"
        },
        {
          "label": "Tier 1 Preferred Generic - 100-day Preferred Mail",
          "value": "$0"
        },
        {
          "label": "Tier 1 Preferred Generic - 100-day Standard Mail",
          "value": "$6"
        },
        {
          "label": "Tier 2 Generic - 30-day Preferred Retail",
          "value": "$0"
        },
        {
          "label": "Tier 2 Generic - 30-day Standard Retail",
          "value": "$12"
        },
        {
          "label": "Tier 2 Generic - 30-day Preferred Mail",
          "value": "$0"
        },
        {
          "label": "Tier 2 Generic - 30-day Standard Mail",
          "value": "$12"
        },
        {
          "label": "Tier 2 Generic - 31-day LTC",
          "value": "$12"
        },
        {
          "label": "Tier 2 Generic - 100-day Preferred Retail",
          "value": "$0"
        },
        {
          "label": "Tier 2 Generic - 100-day Standard Retail",
          "value": "$36"
        },
        {
          "label": "Tier 2 Generic - 100-day Preferred Mail",
          "value": "$0"
        },
        {
          "label": "Tier 2 Generic - 100-day Standard Mail",
          "value": "$36"
        },
        {
          "label": "Tier 3 Preferred Brand - 30-day",
          "value": "24%"
        },
        {
          "label": "Tier 3 Preferred Brand - 100-day",
          "value": "24%"
        },
        {
          "label": "Tier 4 Non-Preferred Drug - 30-day",
          "value": "25%"
        },
        {
          "label": "Tier 4 Non-Preferred Drug - 100-day",
          "value": "25%"
        },
        {
          "label": "Tier 5 Specialty - 30-day",
          "value": "25%"
        },
        {
          "label": "Out-of-pocket threshold",
          "value": "$2,100"
        },
        {
          "label": "Catastrophic coverage",
          "value": "$0"
        },
        {
          "label": "Part D Insulin",
          "value": "$35 max per month"
        },
        {
          "label": "Part B Insulin",
          "value": "$35"
        },
        {
          "label": "Chemotherapy drugs",
          "value": "0%-20% in-network, 50% out-of-network"
        },
        {
          "label": "Other Part B drugs",
          "value": "0%-20% in-network, 50% out-of-network"
        }
      ]
    },
    {
      "title": "Plan Resources",
      "icon": "phone",
      "rows": [
        {
          "label": "Member Phone",
          "value": "(800)282-5366"
        },
        {
          "label": "Member Phone (Local)",
          "value": "(800)282-5366"
        },
        {
          "label": "Prospective Member Phone",
          "value": "(833)859-6031"
        },
        {
          "label": "TTY",
          "value": "711"
        },
        {
          "label": "Provider Directory",
          "value": "www.aetnamedicare.com/findprovider"
        },
        {
          "label": "Formulary",
          "value": "www.aetnamedicare.com/formulary"
        },
        {
          "label": "Pharmacy Directory",
          "value": "www.aetnamedicare.com/findpharmacy"
        },
        {
          "label": "Website",
          "value": "www.aetna.com/medicare"
        }
      ]
    }
  ]
}