{
  "carrier": "Blue Cross and Blue Shield of North Carolina",
  "contract_number": "H3449",
  "org_name": "BLUE CROSS AND BLUE SHIELD OF NORTH CAROLINA",
  "geographic_area": "Select North Carolina Counties",
  "source": "CMS PBP 2026",
  "star_rating_overall": 4.0,
  "star_rating_part_c": 4.5,
  "star_rating_part_d": 4.0,
  "plan_id": "H3449-027-001",
  "plan_id_full": "H3449-027-001",
  "states": "NC",
  "counties_count": "20",
  "plan_name": "Blue Medicare Essential (HMO) H3449-027-001",
  "plan_type": "HMO",
  "monthly_premium": "$0",
  "annual_deductible_in": "$0",
  "moop_in": "$9,250",
  "moop_out": "Not covered",
  "part_b_premium_reduction": "$42.50",
  "drug_deductible": "$615",
  "sections": [
    {
      "title": "Key Benefits",
      "icon": "heart-pulse",
      "rows": [
        {
          "label": "PCP visit",
          "value": "$5"
        },
        {
          "label": "Specialist visit",
          "value": "$45"
        },
        {
          "label": "Urgent care",
          "value": "$40"
        },
        {
          "label": "Emergency room",
          "value": "$115"
        },
        {
          "label": "Inpatient hospital",
          "value": "$407/day days 1-6, $0/day days 7-90, $0/day 91+"
        },
        {
          "label": "Ambulance",
          "value": "$275"
        },
        {
          "label": "Lab services PCP office",
          "value": "$0"
        },
        {
          "label": "X-rays PCP office",
          "value": "$0"
        },
        {
          "label": "Advanced imaging MRI/CT PCP office",
          "value": "$0"
        },
        {
          "label": "PET scan PCP office",
          "value": "$0"
        },
        {
          "label": "Mental health inpatient",
          "value": "$407/day days 1-5, $0/day days 6-90"
        },
        {
          "label": "Part B Giveback",
          "value": "$42.50"
        }
      ]
    },
    {
      "title": "Supplemental Benefits",
      "icon": "hand-holding-heart",
      "rows": [
        {
          "label": "Fitness benefit",
          "value": "SilverSneakers gym membership and digital platform access"
        },
        {
          "label": "Meals benefit",
          "value": "Two meals per day for 14 days post-discharge"
        },
        {
          "label": "Caregiver support",
          "value": "Support and resources for non-professional caregivers"
        },
        {
          "label": "Personal emergency response system",
          "value": "Wearable device with fast access to emergency services"
        }
      ]
    },
    {
      "title": "Diagnostic Tests & Imaging",
      "icon": "microscope",
      "rows": [
        {
          "label": "Lab services other setting",
          "value": "$5"
        },
        {
          "label": "X-rays other setting",
          "value": "$15"
        },
        {
          "label": "Advanced imaging MRI/CT other setting",
          "value": "Lesser of 20% or $150"
        },
        {
          "label": "PET scan other setting",
          "value": "$300"
        }
      ]
    },
    {
      "title": "Specialty & Therapy Care",
      "icon": "stethoscope",
      "rows": [
        {
          "label": "Mental health outpatient",
          "value": "$40"
        },
        {
          "label": "Physical therapy",
          "value": "$25"
        },
        {
          "label": "Occupational therapy",
          "value": "$25"
        },
        {
          "label": "Cardiac rehabilitation",
          "value": "$0"
        },
        {
          "label": "Pulmonary rehabilitation",
          "value": "$15"
        },
        {
          "label": "Podiatry",
          "value": "$45"
        }
      ]
    },
    {
      "title": "Home & Post-Acute Care",
      "icon": "house-medical",
      "rows": [
        {
          "label": "Skilled nursing facility",
          "value": "$0/day days 1-20, $218/day days 21-100"
        },
        {
          "label": "Durable medical equipment",
          "value": "20%"
        }
      ]
    },
    {
      "title": "Other Medical Services",
      "icon": "hospital",
      "rows": [
        {
          "label": "Preventive care",
          "value": "$0"
        },
        {
          "label": "Outpatient hospital",
          "value": "$0-$335"
        },
        {
          "label": "Outpatient surgery",
          "value": "$0-$300"
        },
        {
          "label": "Diabetic supplies preferred",
          "value": "$0"
        },
        {
          "label": "Diabetic supplies non-preferred",
          "value": "20%"
        },
        {
          "label": "Diabetic shoes",
          "value": "20%"
        },
        {
          "label": "Part B insulin",
          "value": "$35/30-day"
        },
        {
          "label": "Part B chemotherapy",
          "value": "0-20%"
        }
      ]
    },
    {
      "title": "Prescription Drugs",
      "icon": "pills",
      "rows": [
        {
          "label": "Drug deductible Tiers 1,2,6",
          "value": "$0"
        },
        {
          "label": "Drug deductible Tiers 3,4,5",
          "value": "$615"
        },
        {
          "label": "Tier 1 Preferred Generic 30-day preferred retail",
          "value": "$0"
        },
        {
          "label": "Tier 1 Preferred Generic 90-day preferred retail",
          "value": "$0"
        },
        {
          "label": "Tier 1 Preferred Generic 90-day mail order",
          "value": "$0"
        },
        {
          "label": "Tier 1 Preferred Generic 30-day standard retail",
          "value": "$15"
        },
        {
          "label": "Tier 1 Preferred Generic 90-day standard retail",
          "value": "$45"
        },
        {
          "label": "Tier 2 Generic 30-day preferred retail",
          "value": "$4"
        },
        {
          "label": "Tier 2 Generic 90-day preferred retail",
          "value": "$12"
        },
        {
          "label": "Tier 2 Generic 90-day mail order",
          "value": "$0"
        },
        {
          "label": "Tier 2 Generic 30-day standard retail",
          "value": "$20"
        },
        {
          "label": "Tier 2 Generic 90-day standard retail",
          "value": "$60"
        },
        {
          "label": "Tier 3 Preferred Brand 30-day preferred retail",
          "value": "25%"
        },
        {
          "label": "Tier 3 Preferred Brand 90-day preferred retail",
          "value": "25%"
        },
        {
          "label": "Tier 3 Preferred Brand 90-day mail order",
          "value": "25%"
        },
        {
          "label": "Tier 3 Preferred Brand 30-day standard retail",
          "value": "25%"
        },
        {
          "label": "Tier 3 Preferred Brand 90-day standard retail",
          "value": "25%"
        },
        {
          "label": "Tier 4 Non-Preferred 30-day preferred retail",
          "value": "25%"
        },
        {
          "label": "Tier 4 Non-Preferred 90-day preferred retail",
          "value": "25%"
        },
        {
          "label": "Tier 4 Non-Preferred 90-day mail order",
          "value": "25%"
        },
        {
          "label": "Tier 4 Non-Preferred 30-day standard retail",
          "value": "25%"
        },
        {
          "label": "Tier 4 Non-Preferred 90-day standard retail",
          "value": "25%"
        },
        {
          "label": "Tier 5 Specialty 30-day preferred retail",
          "value": "25%"
        },
        {
          "label": "Tier 5 Specialty 30-day standard retail",
          "value": "25%"
        },
        {
          "label": "Tier 6 Select Care 30-day preferred retail",
          "value": "$0"
        },
        {
          "label": "Tier 6 Select Care 90-day preferred retail",
          "value": "$0"
        },
        {
          "label": "Tier 6 Select Care 90-day mail order",
          "value": "$0"
        },
        {
          "label": "Tier 6 Select Care 30-day standard retail",
          "value": "$3"
        },
        {
          "label": "Tier 6 Select Care 90-day standard retail",
          "value": "$3"
        },
        {
          "label": "Insulin Tier 3 30-day preferred retail",
          "value": "$35"
        },
        {
          "label": "Insulin Tier 3 90-day preferred retail",
          "value": "$105"
        },
        {
          "label": "Insulin Tier 3 90-day mail order",
          "value": "$105"
        },
        {
          "label": "Insulin Tier 3 30-day standard retail",
          "value": "$35"
        },
        {
          "label": "Insulin Tier 3 90-day standard retail",
          "value": "$105"
        },
        {
          "label": "Insulin Tier 4 30-day preferred retail",
          "value": "$35"
        },
        {
          "label": "Insulin Tier 4 90-day preferred retail",
          "value": "$105"
        },
        {
          "label": "Insulin Tier 4 90-day mail order",
          "value": "$105"
        },
        {
          "label": "Insulin Tier 4 30-day standard retail",
          "value": "$35"
        },
        {
          "label": "Insulin Tier 4 90-day standard retail",
          "value": "$105"
        },
        {
          "label": "Catastrophic coverage",
          "value": "$0"
        }
      ]
    },
    {
      "title": "Plan Resources",
      "icon": "phone",
      "rows": [
        {
          "label": "Member Phone",
          "value": "(888)310-4110"
        },
        {
          "label": "Member Phone (Local)",
          "value": "(888)310-4110"
        },
        {
          "label": "Prospective Member Phone",
          "value": "(866)760-0823"
        },
        {
          "label": "TTY",
          "value": "711"
        },
        {
          "label": "Provider Directory",
          "value": "https://www.bluecrossnc.com/find-a-doctor-or-facility/medicare"
        },
        {
          "label": "Formulary",
          "value": "https://medicare.bluecrossnc.com/prescription-drug-coverage"
        },
        {
          "label": "Pharmacy Directory",
          "value": "https://medicare.bluecrossnc.com/prescription-drug-coverage"
        },
        {
          "label": "Website",
          "value": "https://www.bluecrossnc.com/medicare"
        }
      ]
    }
  ]
}