{
  "plan_id": "H5299-002",
  "carrier": "Devoted Health",
  "contract_number": "H5299",
  "org_name": "DEVOTED HEALTH PLAN OF NORTH CAROLINA INC",
  "geographic_area": "North Carolina Triad",
  "states": "NC",
  "counties_count": "11",
  "source": "CMS PBP 2026",
  "star_rating_overall": 5.0,
  "star_rating_part_c": 5.0,
  "star_rating_part_d": 4.5,
  "plan_name": "DEVOTED GIVEBACK 002 NC (HMO)",
  "plan_type": "HMO",
  "monthly_premium": "$0",
  "annual_deductible_in": "$0",
  "moop_in": "$6,700",
  "moop_out": "Not covered",
  "part_b_premium_reduction": "$184.70",
  "drug_deductible": "$605",
  "sections": [
    {
      "title": "Key Benefits",
      "icon": "heart-pulse",
      "rows": [
        {
          "label": "PCP visit",
          "value": "$0"
        },
        {
          "label": "Specialist visit",
          "value": "$45"
        },
        {
          "label": "Urgent care",
          "value": "$45"
        },
        {
          "label": "Emergency room",
          "value": "$130"
        },
        {
          "label": "Inpatient hospital",
          "value": "$395/day days 1-5, $0/day day 6+"
        },
        {
          "label": "Ambulance",
          "value": "$315 ground, 20% air"
        },
        {
          "label": "Mental health (inpatient)",
          "value": "$395/day days 1-5, $0/day days 6-90"
        },
        {
          "label": "Part B Giveback",
          "value": "$184.70"
        }
      ]
    },
    {
      "title": "Dental",
      "icon": "tooth",
      "rows": [
        {
          "label": "Dental card",
          "value": "$500 per year preloaded debit card"
        }
      ]
    },
    {
      "title": "Vision",
      "icon": "eye",
      "rows": [
        {
          "label": "Vision eyewear allowance",
          "value": "$200 per year"
        }
      ]
    },
    {
      "title": "Hearing",
      "icon": "ear-listen",
      "rows": [
        {
          "label": "Hearing aid benefit",
          "value": "Covered — see Summary of Benefits"
        }
      ]
    },
    {
      "title": "Supplemental Benefits",
      "icon": "hand-holding-heart",
      "rows": [
        {
          "label": "OTC allowance",
          "value": "$24 per quarter"
        },
        {
          "label": "SilverSneakers fitness",
          "value": "$0 membership"
        },
        {
          "label": "Wellness Bucks",
          "value": "$150 per year toward fitness and wellness items"
        },
        {
          "label": "Worldwide emergency coverage",
          "value": "Covered as supplemental benefit"
        },
        {
          "label": "Enhanced prescription drugs",
          "value": "Tier 2 cost-sharing for folic acid 1mg"
        }
      ]
    },
    {
      "title": "Diagnostic Tests & Imaging",
      "icon": "microscope",
      "rows": [
        {
          "label": "Lab services",
          "value": "$0 office, $20 hospital"
        },
        {
          "label": "X-rays/diagnostic imaging",
          "value": "$0-$25 office, $75 hospital"
        },
        {
          "label": "Advanced imaging (CT/MRI/PET)",
          "value": "$100-$200 office, $200-$300 hospital"
        },
        {
          "label": "Diagnostic tests and procedures",
          "value": "$0-$40 office, $95 hospital"
        }
      ]
    },
    {
      "title": "Specialty & Therapy Care",
      "icon": "stethoscope",
      "rows": [
        {
          "label": "Mental health (outpatient)",
          "value": "$45"
        },
        {
          "label": "Chiropractic",
          "value": "$15"
        },
        {
          "label": "Podiatry/foot care",
          "value": "$45"
        },
        {
          "label": "Physical therapy",
          "value": "$45 office, $50 hospital"
        },
        {
          "label": "Occupational therapy",
          "value": "$45 office, $50 hospital"
        },
        {
          "label": "Speech therapy",
          "value": "$45 office, $50 hospital"
        }
      ]
    },
    {
      "title": "Home & Post-Acute Care",
      "icon": "house-medical",
      "rows": [
        {
          "label": "Skilled nursing facility",
          "value": "$0/day days 1-20, $218/day days 21-100"
        },
        {
          "label": "Home health care",
          "value": "$0"
        },
        {
          "label": "Durable medical equipment (DME)",
          "value": "20% basic, 50% advanced"
        },
        {
          "label": "Kidney disease/dialysis",
          "value": "20%"
        }
      ]
    },
    {
      "title": "Other Medical Services",
      "icon": "hospital",
      "rows": [
        {
          "label": "Preventive care",
          "value": "$0"
        },
        {
          "label": "Outpatient surgery/services",
          "value": "$495 hospital, $395 ASC"
        },
        {
          "label": "Prosthetics/orthotics",
          "value": "20%"
        },
        {
          "label": "Diabetic supplies/monitoring",
          "value": "$0 supplies, $0 CGM retail, 50% CGM DME"
        },
        {
          "label": "Radiation therapy",
          "value": "20%"
        },
        {
          "label": "Observation stays",
          "value": "$395"
        },
        {
          "label": "Diabetic shoes",
          "value": "$0"
        }
      ]
    },
    {
      "title": "Prescription Drugs",
      "icon": "pills",
      "rows": [
        {
          "label": "Drug deductible",
          "value": "$605 tiers 3-5 only"
        },
        {
          "label": "Tier 1 30-day retail",
          "value": "$0"
        },
        {
          "label": "Tier 2 30-day retail",
          "value": "$3"
        },
        {
          "label": "Tier 3 30-day retail",
          "value": "22%"
        },
        {
          "label": "Tier 4 30-day retail",
          "value": "25%"
        },
        {
          "label": "Tier 5 30-day retail",
          "value": "25%"
        },
        {
          "label": "Tier 1 100-day mail",
          "value": "$0"
        },
        {
          "label": "Tier 2 100-day mail",
          "value": "$7.50"
        },
        {
          "label": "Tier 3 100-day mail",
          "value": "22%"
        },
        {
          "label": "Tier 4 100-day mail",
          "value": "25%"
        },
        {
          "label": "Catastrophic coverage",
          "value": "$0 after $2,100 out-of-pocket"
        },
        {
          "label": "Insulin coverage",
          "value": "$35 max per 30-day supply"
        },
        {
          "label": "Part B drugs chemotherapy",
          "value": "20%"
        },
        {
          "label": "Part B drugs other",
          "value": "20%"
        },
        {
          "label": "Enhanced drugs",
          "value": "$3 Tier 2 cost-sharing for folic acid, vitamin D, B12 injection, sildenafil, tadalafil"
        }
      ]
    },
    {
      "title": "Plan Resources",
      "icon": "phone",
      "rows": [
        {
          "label": "Member Phone",
          "value": "(800)338-6833"
        },
        {
          "label": "Member Phone (Local)",
          "value": "(800)338-6833"
        },
        {
          "label": "Prospective Member Phone",
          "value": "(844)978-2770"
        },
        {
          "label": "TTY",
          "value": "711"
        },
        {
          "label": "Provider Directory",
          "value": "www.Devoted.com"
        },
        {
          "label": "Formulary",
          "value": "www.Devoted.com"
        },
        {
          "label": "Pharmacy Directory",
          "value": "www.Devoted.com"
        },
        {
          "label": "Website",
          "value": "www.Devoted.com"
        }
      ]
    }
  ]
}