{
  "plan_id": "H2816-013",
  "carrier": "Wellcare",
  "contract_number": "H2816",
  "org_name": "AMERICAN PROGRESSIVE LIFE & HLTH INS COMPANY OF NY",
  "geographic_area": "Select counties in NY",
  "states": "NY",
  "counties_count": "25",
  "source": "CMS PBP 2026",
  "star_rating_overall": 3.5,
  "star_rating_part_c": 3.0,
  "star_rating_part_d": 4.5,
  "plan_name": "Wellcare Premium Ultra (PFFS)",
  "plan_type": "PFFS",
  "monthly_premium": "$127",
  "annual_deductible_in": "$0 medical",
  "moop_in": "$3,400 combined",
  "moop_out": "$3,400 combined",
  "moop_combined": "$3,400",
  "drug_deductible": "$615",
  "sections": [
    {
      "title": "Key Benefits",
      "icon": "heart-pulse",
      "rows": [
        {
          "label": "PCP visit (in-network)",
          "value": "$0"
        },
        {
          "label": "PCP visit (out-of-network)",
          "value": "$10"
        },
        {
          "label": "Specialist visit (in-network)",
          "value": "$20"
        },
        {
          "label": "Specialist visit (out-of-network)",
          "value": "$35"
        },
        {
          "label": "Urgent care",
          "value": "$35"
        },
        {
          "label": "Emergency room",
          "value": "$150"
        },
        {
          "label": "Inpatient hospital (in-network)",
          "value": "$500/stay days 1-90, $0/day days 91-120"
        },
        {
          "label": "Inpatient hospital (out-of-network)",
          "value": "$300/day days 1-7, $0/day days 8-90"
        },
        {
          "label": "Ambulance",
          "value": "$350"
        },
        {
          "label": "Mental health (inpatient) (in-network)",
          "value": "$500/stay days 1-90"
        },
        {
          "label": "Mental health (inpatient) (out-of-network)",
          "value": "$300/day days 1-7, $0/day days 8-90"
        }
      ]
    },
    {
      "title": "Dental",
      "icon": "tooth",
      "rows": [
        {
          "label": "Dental allowance",
          "value": "Up to $2,000 per year for comprehensive dental services"
        }
      ]
    },
    {
      "title": "Vision",
      "icon": "eye",
      "rows": [
        {
          "label": "Vision allowance",
          "value": "Up to $100 per year for contacts and glasses"
        }
      ]
    },
    {
      "title": "Supplemental Benefits",
      "icon": "hand-holding-heart",
      "rows": [
        {
          "label": "Worldwide emergency coverage",
          "value": "$150 copay, $50,000 maximum coverage"
        },
        {
          "label": "Worldwide urgent care coverage",
          "value": "$150 copay, $50,000 maximum coverage"
        },
        {
          "label": "Virtual visits",
          "value": "$0 copay, 24/7 access to board certified doctors"
        },
        {
          "label": "Social support platform",
          "value": "$0 copay, online platform for mental health support"
        },
        {
          "label": "Fitness program",
          "value": "$0 copay"
        },
        {
          "label": "24-Hour nurse advice line",
          "value": "$0 copay"
        },
        {
          "label": "Chronic respiratory management program",
          "value": "0% coinsurance for nebulizer"
        },
        {
          "label": "My Wellcare Rewards",
          "value": "Up to $100 for completing health activities"
        },
        {
          "label": "Health and wellness education programs",
          "value": "Various programs available"
        },
        {
          "label": "Enhanced excluded drug coverage",
          "value": "Tier 1 folic acid"
        }
      ]
    },
    {
      "title": "Diagnostic Tests & Imaging",
      "icon": "microscope",
      "rows": [
        {
          "label": "Lab services (in-network)",
          "value": "$0, $50 genetic testing"
        },
        {
          "label": "Lab services (out-of-network)",
          "value": "30%"
        },
        {
          "label": "X-rays/diagnostic imaging (in-network)",
          "value": "$0"
        },
        {
          "label": "X-rays/diagnostic imaging (out-of-network)",
          "value": "30%"
        },
        {
          "label": "Advanced imaging (CT/MRI/PET) (in-network)",
          "value": "$0 mammogram, $200 outpatient, $100 other locations"
        },
        {
          "label": "Advanced imaging (CT/MRI/PET) (out-of-network)",
          "value": "30%"
        },
        {
          "label": "Diagnostic tests (in-network)",
          "value": "$0"
        },
        {
          "label": "Diagnostic tests (out-of-network)",
          "value": "30%"
        },
        {
          "label": "Therapeutic radiology (in-network)",
          "value": "20%"
        },
        {
          "label": "Therapeutic radiology (out-of-network)",
          "value": "30%"
        }
      ]
    },
    {
      "title": "Specialty & Therapy Care",
      "icon": "stethoscope",
      "rows": [
        {
          "label": "Mental health (outpatient) (in-network)",
          "value": "$20"
        },
        {
          "label": "Mental health (outpatient) (out-of-network)",
          "value": "30%"
        },
        {
          "label": "Chiropractic (in-network)",
          "value": "$20"
        },
        {
          "label": "Chiropractic (out-of-network)",
          "value": "30%"
        },
        {
          "label": "Podiatry/foot care (in-network)",
          "value": "$20"
        },
        {
          "label": "Podiatry/foot care (out-of-network)",
          "value": "30%"
        },
        {
          "label": "Physical therapy (in-network)",
          "value": "$20"
        },
        {
          "label": "Physical therapy (out-of-network)",
          "value": "30%"
        },
        {
          "label": "Occupational therapy (in-network)",
          "value": "$20"
        },
        {
          "label": "Occupational therapy (out-of-network)",
          "value": "30%"
        },
        {
          "label": "Pulmonary rehabilitation (in-network)",
          "value": "$40"
        },
        {
          "label": "Pulmonary rehabilitation (out-of-network)",
          "value": "30%"
        },
        {
          "label": "Acupuncture (in-network)",
          "value": "$0 PCP office, $20 chiropractor/specialist"
        },
        {
          "label": "Acupuncture (out-of-network)",
          "value": "$10 PCP office, 30% chiropractor, $35 specialist"
        },
        {
          "label": "Opioid treatment (in-network)",
          "value": "$20"
        },
        {
          "label": "Opioid treatment (out-of-network)",
          "value": "$35"
        }
      ]
    },
    {
      "title": "Home & Post-Acute Care",
      "icon": "house-medical",
      "rows": [
        {
          "label": "Skilled nursing facility (in-network)",
          "value": "$0/day days 1-20, $218/day days 21-40, $0/day days 41-100"
        },
        {
          "label": "Skilled nursing facility (out-of-network)",
          "value": "$0/day days 1-20, $218/day days 21-100"
        },
        {
          "label": "Home health care (in-network)",
          "value": "$0"
        },
        {
          "label": "Home health care (out-of-network)",
          "value": "30%"
        },
        {
          "label": "Durable medical equipment (DME) (in-network)",
          "value": "20%"
        },
        {
          "label": "Durable medical equipment (DME) (out-of-network)",
          "value": "30%"
        }
      ]
    },
    {
      "title": "Other Medical Services",
      "icon": "hospital",
      "rows": [
        {
          "label": "Preventive care",
          "value": "$0"
        },
        {
          "label": "Outpatient surgery/services (in-network)",
          "value": "$0 skin biopsies, $200 other services"
        },
        {
          "label": "Outpatient surgery/services (out-of-network)",
          "value": "30%"
        },
        {
          "label": "Outpatient observation (in-network)",
          "value": "$150 via ER, $200 via outpatient"
        },
        {
          "label": "Outpatient observation (out-of-network)",
          "value": "30%"
        },
        {
          "label": "Ambulatory surgical center (in-network)",
          "value": "$150"
        },
        {
          "label": "Ambulatory surgical center (out-of-network)",
          "value": "30%"
        },
        {
          "label": "Telehealth/virtual visits",
          "value": "$0"
        },
        {
          "label": "Prosthetics/orthotics (in-network)",
          "value": "20%"
        },
        {
          "label": "Prosthetics/orthotics (out-of-network)",
          "value": "30%"
        },
        {
          "label": "Diabetic supplies/monitoring (in-network)",
          "value": "$0"
        },
        {
          "label": "Diabetic supplies/monitoring (out-of-network)",
          "value": "30%"
        },
        {
          "label": "Diabetic shoes/inserts (in-network)",
          "value": "20%"
        },
        {
          "label": "Diabetic shoes/inserts (out-of-network)",
          "value": "30%"
        },
        {
          "label": "Annual routine physical",
          "value": "$0"
        }
      ]
    },
    {
      "title": "Prescription Drugs",
      "icon": "pills",
      "rows": [
        {
          "label": "Drug deductible",
          "value": "$615 for Tiers 3-5"
        },
        {
          "label": "Tier 1 Preferred Generic - Preferred Retail 30-day",
          "value": "$0"
        },
        {
          "label": "Tier 1 Preferred Generic - Preferred Retail 100-day",
          "value": "$0"
        },
        {
          "label": "Tier 1 Preferred Generic - Standard Retail 30-day",
          "value": "$5"
        },
        {
          "label": "Tier 1 Preferred Generic - Standard Retail 100-day",
          "value": "$15"
        },
        {
          "label": "Tier 1 Preferred Generic - Mail Order 100-day",
          "value": "$0 preferred, $15 standard"
        },
        {
          "label": "Tier 2 Generic - Preferred Retail 30-day",
          "value": "$0"
        },
        {
          "label": "Tier 2 Generic - Preferred Retail 100-day",
          "value": "$0"
        },
        {
          "label": "Tier 2 Generic - Standard Retail 30-day",
          "value": "$10"
        },
        {
          "label": "Tier 2 Generic - Standard Retail 100-day",
          "value": "$30"
        },
        {
          "label": "Tier 2 Generic - Mail Order 100-day",
          "value": "$0 preferred, $30 standard"
        },
        {
          "label": "Tier 3 Preferred Brand - Preferred Retail 30-day",
          "value": "25%"
        },
        {
          "label": "Tier 3 Preferred Brand - Preferred Retail 100-day",
          "value": "25%"
        },
        {
          "label": "Tier 3 Preferred Brand - Standard Retail 30-day",
          "value": "25%"
        },
        {
          "label": "Tier 3 Preferred Brand - Standard Retail 100-day",
          "value": "25%"
        },
        {
          "label": "Tier 3 Preferred Brand - Mail Order 100-day",
          "value": "25%"
        },
        {
          "label": "Tier 4 Non-Preferred Drug - Preferred Retail 30-day",
          "value": "37%"
        },
        {
          "label": "Tier 4 Non-Preferred Drug - Preferred Retail 100-day",
          "value": "37%"
        },
        {
          "label": "Tier 4 Non-Preferred Drug - Standard Retail 30-day",
          "value": "38%"
        },
        {
          "label": "Tier 4 Non-Preferred Drug - Standard Retail 100-day",
          "value": "38%"
        },
        {
          "label": "Tier 4 Non-Preferred Drug - Mail Order 100-day",
          "value": "37% preferred, 38% standard"
        },
        {
          "label": "Tier 5 Specialty - 30-day only",
          "value": "25%"
        },
        {
          "label": "Tier 6 Select Care Drugs",
          "value": "$0"
        },
        {
          "label": "Part B drugs",
          "value": "20% in-network, 30% out-of-network"
        },
        {
          "label": "Insulin",
          "value": "$35 max per month"
        },
        {
          "label": "Allergy antigen",
          "value": "0%"
        },
        {
          "label": "Catastrophic coverage",
          "value": "$0"
        }
      ]
    },
    {
      "title": "Plan Resources",
      "icon": "phone",
      "rows": [
        {
          "label": "Member Phone",
          "value": "(833)444-9088"
        },
        {
          "label": "Member Phone (Local)",
          "value": "(833)444-9088"
        },
        {
          "label": "Prospective Member Phone",
          "value": "(844)480-0680"
        },
        {
          "label": "TTY",
          "value": "711"
        },
        {
          "label": "Provider Directory",
          "value": "go.wellcare.com/Medicare"
        },
        {
          "label": "Formulary",
          "value": "go.wellcare.com/Medicare"
        },
        {
          "label": "Pharmacy Directory",
          "value": "go.wellcare.com/Medicare"
        },
        {
          "label": "Website",
          "value": "go.wellcare.com/Medicare"
        }
      ]
    }
  ],
  "plan_id_full": "H2816-013-000"
}